src/__init__.py
src/hibp_harvester.py
hibp_harvester-1.0.8.dist-info/LICENSE
hibp_harvester-1.0.8.dist-info/METADATA
hibp_harvester-1.0.8.dist-info/WHEEL
hibp_harvester-1.0.8.dist-info/entry_points.txt
hibp_harvester-1.0.8.dist-info/top_level.txt
hibp_harvester-1.0.8.dist-info/RECORD
