Metadata-Version: 2.1
Name: hibp-harvester
Version: 1.0.8
Summary: A python tool to harvest haveibeenpwned.com via domain search
Home-page: https://github.com/security-companion/hibp-harvester
Author: Joachim Mammele
Classifier: Programming Language :: Python :: 3
Classifier: License :: OSI Approved :: MIT License
Classifier: Operating System :: OS Independent
License-File: LICENSE
Requires-Dist: click
Requires-Dist: requests
